CC_API_jh2/CC_API_jh2.py
CC_API_jh2/__init__.py
CC_API_jh2-0.11.511.dist-info/LICENSE
CC_API_jh2-0.11.511.dist-info/LICENSE.txt
CC_API_jh2-0.11.511.dist-info/METADATA
CC_API_jh2-0.11.511.dist-info/WHEEL
CC_API_jh2-0.11.511.dist-info/top_level.txt
CC_API_jh2-0.11.511.dist-info/RECORD
